{
    "version": 1,
    "#comment": "FM47",
    "objects": [
        {
            "objclass": "LevelDefinition",
            "objdata": {
                "Name": "[OYKUS_LEVEL_NAME_MA]",
                "Modules": [
                    "RTID(StandardIntro@LevelModules)",
                    "RTID(DefaultSunDropper@LevelModules)",
                    "RTID(ZombiesDeadWinCon@LevelModules)",
                    "RTID(DefaultZombieWinCondition@LevelModules)",
                    "RTID(ModernMowers@LevelModules)",
                    "RTID(ChallengeModule@CurrentLevel)",
                    "RTID(GoldTiles@CurrentLevel)",
                    "RTID(SeedBank@CurrentLevel)",
                    "RTID(NewWaves@CurrentLevel)"
                ],
                "StageModule": "RTID(ModernStage@LevelModules)",
                "Description": "[PLAYERS_TRIP_TO_OYKUS]",
                "Loot": "RTID(NoLoot@LevelModules)",
                "LevelNumber": 47
            }
        },
        {
            "aliases": [
                "ChallengeModule"
            ],
            "objdata": {
                "Challenges": [
                    [
                        "RTID(SunProduced@CurrentLevel)",
                        "RTID(KillZombies@CurrentLevel)"
                    ]
                ],
                "ChallengesAlwaysAvailable": true
            },
            "objclass": "StarChallengeModuleProperties"
        },
        {
            "aliases": [
                "SunProduced"
            ],
            "objdata": {
                "TargetSun": 14100
            },
            "objclass": "StarChallengeSunProducedProps"
        },
        {
            "aliases": [
                "KillZombies"
            ],
            "objdata": {
                "ZombiesToKill": 120,
                "Time": 20
            },
            "objclass": "StarChallengeKillZombiesInTimeProps"
        },
        {
            "aliases": [
                "GoldTiles"
            ],
            "objdata": {
                "InitialGridItemPlacements": [
                    {
                        "GridX": 5,
                        "GridY": 0,
                        "TypeName": "goldtile"
                    },
                    {
                        "GridX": 7,
                        "GridY": 0,
                        "TypeName": "goldtile"
                    },
                    {
                        "GridX": 6,
                        "GridY": 1,
                        "TypeName": "goldtile"
                    },
                    {
                        "GridX": 8,
                        "GridY": 1,
                        "TypeName": "goldtile"
                    },
                    {
                        "GridX": 0,
                        "GridY": 2,
                        "TypeName": "goldtile"
                    },
                    {
                        "GridX": 2,
                        "GridY": 2,
                        "TypeName": "goldtile"
                    },
                    {
                        "GridX": 4,
                        "GridY": 2,
                        "TypeName": "goldtile"
                    },
                    {
                        "GridX": 6,
                        "GridY": 2,
                        "TypeName": "goldtile"
                    },
                    {
                        "GridX": 6,
                        "GridY": 3,
                        "TypeName": "goldtile"
                    },
                    {
                        "GridX": 8,
                        "GridY": 3,
                        "TypeName": "goldtile"
                    },
                    {
                        "GridX": 5,
                        "GridY": 4,
                        "TypeName": "goldtile"
                    },
                    {
                        "GridX": 7,
                        "GridY": 4,
                        "TypeName": "goldtile"
                    }
                ]
            },
            "objclass": "InitialGridItemProperties"
        },
        {
            "aliases": [
                "SeedBank"
            ],
            "objdata": {
                "SelectionMethod": "chooser"
            },
            "objclass": "SeedBankProperties"
        },
        {
            "aliases": [
                "NewWaves"
            ],
            "objdata": {
                "WaveManagerProps": "RTID(WaveManagerProps@CurrentLevel)",
                "DynamicZombies": [
                    {
                        "StartingWave": 3,
                        "PointIncrementPerWave": -40,
                        "StartingPoints": -100,
                        "ZombiePool": [
                            "RTID(tutorial@ZombieTypes)",
                            "RTID(tutorial_armor1@ZombieTypes)",
                            "RTID(tutorial_armor2@ZombieTypes)"
                        ]
                    },
                    {
                        "StartingWave": 4,
                        "PointIncrementPerWave": -25,
                        "StartingPoints": -100,
                        "ZombiePool": [
                            "RTID(tutorial@ZombieTypes)",
                            "RTID(tutorial_armor1@ZombieTypes)",
                            "RTID(tutorial_armor2@ZombieTypes)"
                        ]
                    },
                    {
                        "StartingWave": 5,
                        "PointIncrementPerWave": -10,
                        "StartingPoints": -100,
                        "ZombiePool": [
                            "RTID(tutorial@ZombieTypes)",
                            "RTID(tutorial_armor1@ZombieTypes)",
                            "RTID(tutorial_armor2@ZombieTypes)"
                        ]
                    },
                    {},
                    {
                        "StartingWave": 5,
                        "PointIncrementPerWave": 20,
                        "StartingPoints": 100,
                        "ZombiePool": [
                            "RTID(tutorial@ZombieTypes)",
                            "RTID(tutorial_armor1@ZombieTypes)",
                            "RTID(tutorial_armor2@ZombieTypes)"
                        ]
                    },
                    {
                        "StartingWave": 4,
                        "PointIncrementPerWave": 40,
                        "StartingPoints": 200,
                        "ZombiePool": [
                            "RTID(tutorial@ZombieTypes)",
                            "RTID(tutorial_armor1@ZombieTypes)",
                            "RTID(tutorial_armor2@ZombieTypes)"
                        ]
                    },
                    {
                        "StartingWave": 3,
                        "PointIncrementPerWave": 60,
                        "StartingPoints": 400,
                        "ZombiePool": [
                            "RTID(tutorial@ZombieTypes)",
                            "RTID(tutorial_armor1@ZombieTypes)",
                            "RTID(tutorial_armor2@ZombieTypes)"
                        ]
                    }
                ]
            },
            "objclass": "WaveManagerModuleProperties"
        },
        {
            "aliases": [
                "WaveManagerProps"
            ],
            "objdata": {
                "WaveCount": 18,
                "FlagWaveInterval": 6,
                "Waves": [
                    [
                        "RTID(Wave1@CurrentLevel)"
                    ],
                    [
                        "RTID(Wave2@CurrentLevel)"
                    ],
                    [
                        "RTID(Wave3@CurrentLevel)"
                    ],
                    [
                        "RTID(Wave4@CurrentLevel)"
                    ],
                    [
                        "RTID(Wave5@CurrentLevel)"
                    ],
                    [
                        "RTID(Wave6@CurrentLevel)"
                    ],
                    [
                        "RTID(Wave7@CurrentLevel)"
                    ],
                    [
                        "RTID(Wave8@CurrentLevel)"
                    ],
                    [
                        "RTID(Wave9@CurrentLevel)"
                    ],
                    [
                        "RTID(Wave10@CurrentLevel)"
                    ],
                    [
                        "RTID(Wave11@CurrentLevel)"
                    ],
                    [
                        "RTID(Wave12@CurrentLevel)"
                    ],
                    [
                        "RTID(Wave13@CurrentLevel)"
                    ],
                    [
                        "RTID(Wave14@CurrentLevel)"
                    ],
                    [
                        "RTID(Wave15@CurrentLevel)"
                    ],
                    [
                        "RTID(Wave16@CurrentLevel)"
                    ],
                    [
                        "RTID(Wave17@CurrentLevel)"
                    ],
                    [
                        "RTID(Wave18@CurrentLevel)"
                    ]
                ]
            },
            "objclass": "WaveManagerProperties"
        },
        {
            "aliases": [
                "Wave1"
            ],
            "objdata": {
                "DynamicPlantfood": [
                    1,
                    1,
                    1,
                    1,
                    1,
                    1,
                    0
                ],
                "AdditionalPlantfood": 1,
                "Zombies": [
                    {
                        "Row": "2",
                        "Type": "RTID(lostcity_impporter@ZombieTypes)"
                    },
                    {
                        "Row": "3",
                        "Type": "RTID(ra@ZombieTypes)"
                    }
                ]
            },
            "objclass": "SpawnZombiesJitteredWaveActionProps"
        },
        {
            "aliases": [
                "Wave2"
            ],
            "objdata": {
                "Zombies": [
                    {
                        "Row": "4",
                        "Type": "RTID(modern_newspaper@ZombieTypes)"
                    },
                    {
                        "Row": "4",
                        "Type": "RTID(lostcity_impporter@ZombieTypes)"
                    },
                    {
                        "Row": "5",
                        "Type": "RTID(lostcity_impporter@ZombieTypes)"
                    }
                ]
            },
            "objclass": "SpawnZombiesJitteredWaveActionProps"
        },
        {
            "aliases": [
                "Wave3"
            ],
            "objdata": {
                "Zombies": [
                    {
                        "Row": "1",
                        "Type": "RTID(disco_mech@ZombieTypes)"
                    },
                    {
                        "Row": "3",
                        "Type": "RTID(modern_balloon@ZombieTypes)"
                    }
                ],
                "AdditionalPlantfood": 1
            },
            "objclass": "SpawnZombiesJitteredWaveActionProps"
        },
        {
            "aliases": [
                "Wave4"
            ],
            "objdata": {
                "Zombies": [
                    {
                        "Row": "1",
                        "Type": "RTID(piano@ZombieTypes)"
                    },
                    {
                        "Row": "2",
                        "Type": "RTID(lostcity_impporter@ZombieTypes)"
                    },
                    {
                        "Row": "2",
                        "Type": "RTID(ra@ZombieTypes)"
                    },
                    {
                        "Row": "3",
                        "Type": "RTID(piano@ZombieTypes)"
                    },
                    {
                        "Row": "4",
                        "Type": "RTID(lostcity_impporter@ZombieTypes)"
                    },
                    {
                        "Row": "4",
                        "Type": "RTID(ra@ZombieTypes)"
                    }
                ]
            },
            "objclass": "SpawnZombiesJitteredWaveActionProps"
        },
        {
            "aliases": [
                "Wave5"
            ],
            "objdata": {
                "Zombies": [
                    {
                        "Row": "1",
                        "Type": "RTID(modern_newspaper@ZombieTypes)"
                    },
                    {
                        "Row": "1",
                        "Type": "RTID(tutorial@ZombieTypes)"
                    },
                    {
                        "Row": "2",
                        "Type": "RTID(modern_newspaper@ZombieTypes)"
                    },
                    {
                        "Row": "3",
                        "Type": "RTID(disco_mech@ZombieTypes)"
                    },
                    {
                        "Row": "4",
                        "Type": "RTID(modern_newspaper@ZombieTypes)"
                    },
                    {
                        "Row": "5",
                        "Type": "RTID(modern_newspaper@ZombieTypes)"
                    },
                    {
                        "Row": "5",
                        "Type": "RTID(tutorial@ZombieTypes)"
                    }
                ]
            },
            "objclass": "SpawnZombiesJitteredWaveActionProps"
        },
        {
            "aliases": [
                "Wave6"
            ],
            "objdata": {
                "DynamicPlantfood": [
                    1,
                    1,
                    1,
                    1,
                    1,
                    0,
                    0
                ],
                "AdditionalPlantfood": 1,
                "Zombies": [
                    {
                        "Row": "1",
                        "Type": "RTID(modern_balloon@ZombieTypes)"
                    },
                    {
                        "Row": "1",
                        "Type": "RTID(lostcity_impporter@ZombieTypes)"
                    },
                    {
                        "Row": "1",
                        "Type": "RTID(modern_newspaper@ZombieTypes)"
                    },
                    {
                        "Row": "1",
                        "Type": "RTID(modern_newspaper@ZombieTypes)"
                    },
                    {
                        "Row": "2",
                        "Type": "RTID(modern_balloon@ZombieTypes)"
                    },
                    {
                        "Row": "2",
                        "Type": "RTID(lostcity_impporter@ZombieTypes)"
                    },
                    {
                        "Row": "2",
                        "Type": "RTID(disco_mech@ZombieTypes)"
                    },
                    {
                        "Row": "2",
                        "Type": "RTID(modern_newspaper@ZombieTypes)"
                    },
                    {
                        "Row": "3",
                        "Type": "RTID(modern_balloon@ZombieTypes)"
                    },
                    {
                        "Row": "3",
                        "Type": "RTID(lostcity_impporter@ZombieTypes)"
                    },
                    {
                        "Row": "4",
                        "Type": "RTID(modern_balloon@ZombieTypes)"
                    },
                    {
                        "Row": "4",
                        "Type": "RTID(lostcity_impporter@ZombieTypes)"
                    },
                    {
                        "Row": "4",
                        "Type": "RTID(disco_mech@ZombieTypes)"
                    },
                    {
                        "Row": "4",
                        "Type": "RTID(modern_newspaper@ZombieTypes)"
                    },
                    {
                        "Row": "5",
                        "Type": "RTID(modern_balloon@ZombieTypes)"
                    },
                    {
                        "Row": "5",
                        "Type": "RTID(disco_mech@ZombieTypes)"
                    },
                    {
                        "Row": "5",
                        "Type": "RTID(lostcity_impporter@ZombieTypes)"
                    },
                    {
                        "Row": "5",
                        "Type": "RTID(modern_newspaper@ZombieTypes)"
                    },
                    {
                        "Row": "5",
                        "Type": "RTID(modern_newspaper@ZombieTypes)"
                    }
                ]
            },
            "objclass": "SpawnZombiesJitteredWaveActionProps"
        },
        {
            "aliases": [
                "Wave7"
            ],
            "objdata": {
                "Zombies": [
                    {
                        "Row": "1",
                        "Type": "RTID(ra@ZombieTypes)"
                    },
                    {
                        "Row": "1",
                        "Type": "RTID(modern_newspaper@ZombieTypes)"
                    },
                    {
                        "Row": "2",
                        "Type": "RTID(modern_balloon@ZombieTypes)"
                    },
                    {
                        "Row": "2",
                        "Type": "RTID(ra@ZombieTypes)"
                    },
                    {
                        "Row": "2",
                        "Type": "RTID(modern_newspaper@ZombieTypes)"
                    },
                    {
                        "Row": "3",
                        "Type": "RTID(cowboy_gargantuar@ZombieTypes)"
                    },
                    {
                        "Row": "3",
                        "Type": "RTID(ra@ZombieTypes)"
                    },
                    {
                        "Row": "3",
                        "Type": "RTID(modern_newspaper@ZombieTypes)"
                    },
                    {
                        "Row": "4",
                        "Type": "RTID(modern_balloon@ZombieTypes)"
                    },
                    {
                        "Row": "4",
                        "Type": "RTID(ra@ZombieTypes)"
                    },
                    {
                        "Row": "4",
                        "Type": "RTID(modern_newspaper@ZombieTypes)"
                    },
                    {
                        "Row": "5",
                        "Type": "RTID(ra@ZombieTypes)"
                    },
                    {
                        "Row": "5",
                        "Type": "RTID(modern_newspaper@ZombieTypes)"
                    }
                ]
            },
            "objclass": "SpawnZombiesJitteredWaveActionProps"
        },
        {
            "aliases": [
                "Wave8"
            ],
            "objdata": {
                "Zombies": [
                    {
                        "Row": "1",
                        "Type": "RTID(lostcity_impporter@ZombieTypes)"
                    },
                    {
                        "Row": "1",
                        "Type": "RTID(piano@ZombieTypes)"
                    },
                    {
                        "Row": "2",
                        "Type": "RTID(disco_mech@ZombieTypes)"
                    },
                    {
                        "Row": "2",
                        "Type": "RTID(lostcity_impporter@ZombieTypes)"
                    },
                    {
                        "Row": "3",
                        "Type": "RTID(disco_mech@ZombieTypes)"
                    },
                    {
                        "Row": "3",
                        "Type": "RTID(lostcity_impporter@ZombieTypes)"
                    },
                    {
                        "Row": "4",
                        "Type": "RTID(disco_mech@ZombieTypes)"
                    },
                    {
                        "Row": "4",
                        "Type": "RTID(lostcity_impporter@ZombieTypes)"
                    },
                    {
                        "Row": "5",
                        "Type": "RTID(lostcity_impporter@ZombieTypes)"
                    },
                    {
                        "Row": "5",
                        "Type": "RTID(piano@ZombieTypes)"
                    }
                ]
            },
            "objclass": "SpawnZombiesJitteredWaveActionProps"
        },
        {
            "aliases": [
                "Wave9"
            ],
            "objdata": {
                "Zombies": [
                    {
                        "Row": "1",
                        "Type": "RTID(modern_balloon@ZombieTypes)"
                    },
                    {
                        "Row": "1",
                        "Type": "RTID(modern_balloon@ZombieTypes)"
                    },
                    {
                        "Row": "1",
                        "Type": "RTID(ra@ZombieTypes)"
                    },
                    {
                        "Row": "2",
                        "Type": "RTID(modern_balloon@ZombieTypes)"
                    },
                    {
                        "Row": "2",
                        "Type": "RTID(modern_balloon@ZombieTypes)"
                    },
                    {
                        "Row": "2",
                        "Type": "RTID(lostcity_impporter@ZombieTypes)"
                    },
                    {
                        "Row": "2",
                        "Type": "RTID(lostcity_impporter@ZombieTypes)"
                    },
                    {
                        "Row": "3",
                        "Type": "RTID(modern_balloon@ZombieTypes)"
                    },
                    {
                        "Row": "3",
                        "Type": "RTID(modern_balloon@ZombieTypes)"
                    },
                    {
                        "Row": "3",
                        "Type": "RTID(ra@ZombieTypes)"
                    },
                    {
                        "Row": "4",
                        "Type": "RTID(modern_balloon@ZombieTypes)"
                    },
                    {
                        "Row": "4",
                        "Type": "RTID(modern_balloon@ZombieTypes)"
                    },
                    {
                        "Row": "4",
                        "Type": "RTID(lostcity_impporter@ZombieTypes)"
                    },
                    {
                        "Row": "4",
                        "Type": "RTID(lostcity_impporter@ZombieTypes)"
                    },
                    {
                        "Row": "5",
                        "Type": "RTID(modern_balloon@ZombieTypes)"
                    },
                    {
                        "Row": "5",
                        "Type": "RTID(modern_balloon@ZombieTypes)"
                    },
                    {
                        "Row": "5",
                        "Type": "RTID(ra@ZombieTypes)"
                    }
                ]
            },
            "objclass": "SpawnZombiesJitteredWaveActionProps"
        },
        {
            "aliases": [
                "Wave10"
            ],
            "objdata": {
                "DynamicPlantfood": [
                    1,
                    1,
                    1,
                    1,
                    0,
                    0,
                    0
                ],
                "AdditionalPlantfood": 1,
                "Zombies": [
                    {
                        "Row": "1",
                        "Type": "RTID(piano@ZombieTypes)"
                    },
                    {
                        "Row": "1",
                        "Type": "RTID(modern_newspaper@ZombieTypes)"
                    },
                    {
                        "Row": "2",
                        "Type": "RTID(piano@ZombieTypes)"
                    },
                    {
                        "Row": "2",
                        "Type": "RTID(modern_newspaper@ZombieTypes)"
                    },
                    {
                        "Row": "2",
                        "Type": "RTID(tutorial_armor2@ZombieTypes)"
                    },
                    {
                        "Row": "3",
                        "Type": "RTID(piano@ZombieTypes)"
                    },
                    {
                        "Row": "3",
                        "Type": "RTID(modern_newspaper@ZombieTypes)"
                    },
                    {
                        "Row": "3",
                        "Type": "RTID(tutorial_armor2@ZombieTypes)"
                    },
                    {
                        "Row": "4",
                        "Type": "RTID(piano@ZombieTypes)"
                    },
                    {
                        "Row": "4",
                        "Type": "RTID(modern_newspaper@ZombieTypes)"
                    },
                    {
                        "Row": "4",
                        "Type": "RTID(tutorial_armor2@ZombieTypes)"
                    },
                    {
                        "Row": "5",
                        "Type": "RTID(piano@ZombieTypes)"
                    },
                    {
                        "Row": "5",
                        "Type": "RTID(modern_newspaper@ZombieTypes)"
                    }
                ]
            },
            "objclass": "SpawnZombiesJitteredWaveActionProps"
        },
        {
            "aliases": [
                "Wave11"
            ],
            "objdata": {
                "Zombies": [
                    {
                        "Row": "1",
                        "Type": "RTID(lostcity_impporter@ZombieTypes)"
                    },
                    {
                        "Row": "1",
                        "Type": "RTID(lostcity_impporter@ZombieTypes)"
                    },
                    {
                        "Row": "2",
                        "Type": "RTID(modern_balloon@ZombieTypes)"
                    },
                    {
                        "Row": "2",
                        "Type": "RTID(cowboy_gargantuar@ZombieTypes)"
                    },
                    {
                        "Row": "2",
                        "Type": "RTID(ra@ZombieTypes)"
                    },
                    {
                        "Row": "3",
                        "Type": "RTID(modern_balloon@ZombieTypes)"
                    },
                    {
                        "Row": "3",
                        "Type": "RTID(disco_mech@ZombieTypes)"
                    },
                    {
                        "Row": "3",
                        "Type": "RTID(ra@ZombieTypes)"
                    },
                    {
                        "Row": "4",
                        "Type": "RTID(modern_balloon@ZombieTypes)"
                    },
                    {
                        "Row": "4",
                        "Type": "RTID(cowboy_gargantuar@ZombieTypes)"
                    },
                    {
                        "Row": "4",
                        "Type": "RTID(ra@ZombieTypes)"
                    },
                    {
                        "Row": "5",
                        "Type": "RTID(lostcity_impporter@ZombieTypes)"
                    },
                    {
                        "Row": "5",
                        "Type": "RTID(lostcity_impporter@ZombieTypes)"
                    }
                ]
            },
            "objclass": "SpawnZombiesJitteredWaveActionProps"
        },
        {
            "aliases": [
                "Wave12"
            ],
            "objdata": {
                "Zombies": [
                    {
                        "Row": "1",
                        "Type": "RTID(modern_balloon@ZombieTypes)"
                    },
                    {
                        "Row": "1",
                        "Type": "RTID(disco_mech@ZombieTypes)"
                    },
                    {
                        "Row": "1",
                        "Type": "RTID(lostcity_impporter@ZombieTypes)"
                    },
                    {
                        "Row": "1",
                        "Type": "RTID(tutorial_armor2@ZombieTypes)"
                    },
                    {
                        "Row": "1",
                        "Type": "RTID(modern_newspaper@ZombieTypes)"
                    },
                    {
                        "Row": "2",
                        "Type": "RTID(modern_balloon@ZombieTypes)"
                    },
                    {
                        "Row": "2",
                        "Type": "RTID(disco_mech@ZombieTypes)"
                    },
                    {
                        "Row": "2",
                        "Type": "RTID(piano@ZombieTypes)"
                    },
                    {
                        "Row": "2",
                        "Type": "RTID(lostcity_impporter@ZombieTypes)"
                    },
                    {
                        "Row": "2",
                        "Type": "RTID(tutorial_armor2@ZombieTypes)"
                    },
                    {
                        "Row": "3",
                        "Type": "RTID(disco_mech@ZombieTypes)"
                    },
                    {
                        "Row": "3",
                        "Type": "RTID(lostcity_impporter@ZombieTypes)"
                    },
                    {
                        "Row": "3",
                        "Type": "RTID(tutorial_armor2@ZombieTypes)"
                    },
                    {
                        "Row": "4",
                        "Type": "RTID(modern_balloon@ZombieTypes)"
                    },
                    {
                        "Row": "4",
                        "Type": "RTID(disco_mech@ZombieTypes)"
                    },
                    {
                        "Row": "4",
                        "Type": "RTID(piano@ZombieTypes)"
                    },
                    {
                        "Row": "4",
                        "Type": "RTID(lostcity_impporter@ZombieTypes)"
                    },
                    {
                        "Row": "4",
                        "Type": "RTID(tutorial_armor2@ZombieTypes)"
                    },
                    {
                        "Row": "5",
                        "Type": "RTID(modern_balloon@ZombieTypes)"
                    },
                    {
                        "Row": "5",
                        "Type": "RTID(disco_mech@ZombieTypes)"
                    },
                    {
                        "Row": "5",
                        "Type": "RTID(lostcity_impporter@ZombieTypes)"
                    },
                    {
                        "Row": "5",
                        "Type": "RTID(tutorial_armor2@ZombieTypes)"
                    },
                    {
                        "Row": "5",
                        "Type": "RTID(modern_newspaper@ZombieTypes)"
                    }
                ]
            },
            "objclass": "SpawnZombiesJitteredWaveActionProps"
        },
        {
            "aliases": [
                "Wave13"
            ],
            "objdata": {
                "Zombies": [
                    {
                        "Row": "1",
                        "Type": "RTID(modern_newspaper@ZombieTypes)"
                    },
                    {
                        "Row": "1",
                        "Type": "RTID(tutorial_armor1@ZombieTypes)"
                    },
                    {
                        "Row": "1",
                        "Type": "RTID(tutorial_armor1@ZombieTypes)"
                    },
                    {
                        "Row": "2",
                        "Type": "RTID(disco_mech@ZombieTypes)"
                    },
                    {
                        "Row": "2",
                        "Type": "RTID(modern_newspaper@ZombieTypes)"
                    },
                    {
                        "Row": "2",
                        "Type": "RTID(tutorial_armor1@ZombieTypes)"
                    },
                    {
                        "Row": "2",
                        "Type": "RTID(tutorial_armor1@ZombieTypes)"
                    },
                    {
                        "Row": "3",
                        "Type": "RTID(disco_mech@ZombieTypes)"
                    },
                    {
                        "Row": "3",
                        "Type": "RTID(modern_newspaper@ZombieTypes)"
                    },
                    {
                        "Row": "3",
                        "Type": "RTID(tutorial_armor1@ZombieTypes)"
                    },
                    {
                        "Row": "3",
                        "Type": "RTID(tutorial_armor1@ZombieTypes)"
                    },
                    {
                        "Row": "4",
                        "Type": "RTID(disco_mech@ZombieTypes)"
                    },
                    {
                        "Row": "4",
                        "Type": "RTID(modern_newspaper@ZombieTypes)"
                    },
                    {
                        "Row": "4",
                        "Type": "RTID(tutorial_armor1@ZombieTypes)"
                    },
                    {
                        "Row": "4",
                        "Type": "RTID(tutorial_armor1@ZombieTypes)"
                    },
                    {
                        "Row": "5",
                        "Type": "RTID(modern_newspaper@ZombieTypes)"
                    },
                    {
                        "Row": "5",
                        "Type": "RTID(tutorial_armor1@ZombieTypes)"
                    },
                    {
                        "Row": "5",
                        "Type": "RTID(tutorial_armor1@ZombieTypes)"
                    }
                ]
            },
            "objclass": "SpawnZombiesJitteredWaveActionProps"
        },
        {
            "aliases": [
                "Wave14"
            ],
            "objdata": {
                "Zombies": [
                    {
                        "Row": "1",
                        "Type": "RTID(lostcity_impporter@ZombieTypes)"
                    },
                    {
                        "Row": "1",
                        "Type": "RTID(lostcity_impporter@ZombieTypes)"
                    },
                    {
                        "Row": "1",
                        "Type": "RTID(lostcity_impporter@ZombieTypes)"
                    },
                    {
                        "Row": "2",
                        "Type": "RTID(lostcity_impporter@ZombieTypes)"
                    },
                    {
                        "Row": "2",
                        "Type": "RTID(lostcity_impporter@ZombieTypes)"
                    },
                    {
                        "Row": "2",
                        "Type": "RTID(lostcity_impporter@ZombieTypes)"
                    },
                    {
                        "Row": "3",
                        "Type": "RTID(lostcity_impporter@ZombieTypes)"
                    },
                    {
                        "Row": "3",
                        "Type": "RTID(lostcity_impporter@ZombieTypes)"
                    },
                    {
                        "Row": "3",
                        "Type": "RTID(lostcity_impporter@ZombieTypes)"
                    },
                    {
                        "Row": "3",
                        "Type": "RTID(piano@ZombieTypes)"
                    },
                    {
                        "Row": "4",
                        "Type": "RTID(lostcity_impporter@ZombieTypes)"
                    },
                    {
                        "Row": "4",
                        "Type": "RTID(lostcity_impporter@ZombieTypes)"
                    },
                    {
                        "Row": "4",
                        "Type": "RTID(lostcity_impporter@ZombieTypes)"
                    },
                    {
                        "Row": "5",
                        "Type": "RTID(lostcity_impporter@ZombieTypes)"
                    },
                    {
                        "Row": "5",
                        "Type": "RTID(lostcity_impporter@ZombieTypes)"
                    },
                    {
                        "Row": "5",
                        "Type": "RTID(lostcity_impporter@ZombieTypes)"
                    }
                ]
            },
            "objclass": "SpawnZombiesJitteredWaveActionProps"
        },
        {
            "aliases": [
                "Wave15"
            ],
            "objdata": {
                "Zombies": [
                    {
                        "Row": "1",
                        "Type": "RTID(modern_balloon@ZombieTypes)"
                    },
                    {
                        "Row": "1",
                        "Type": "RTID(disco_mech@ZombieTypes)"
                    },
                    {
                        "Row": "2",
                        "Type": "RTID(modern_balloon@ZombieTypes)"
                    },
                    {
                        "Row": "2",
                        "Type": "RTID(disco_mech@ZombieTypes)"
                    },
                    {
                        "Row": "2",
                        "Type": "RTID(piano@ZombieTypes)"
                    },
                    {
                        "Row": "3",
                        "Type": "RTID(piano@ZombieTypes)"
                    },
                    {
                        "Row": "3",
                        "Type": "RTID(piano@ZombieTypes)"
                    },
                    {
                        "Row": "4",
                        "Type": "RTID(modern_balloon@ZombieTypes)"
                    },
                    {
                        "Row": "4",
                        "Type": "RTID(disco_mech@ZombieTypes)"
                    },
                    {
                        "Row": "4",
                        "Type": "RTID(piano@ZombieTypes)"
                    },
                    {
                        "Row": "5",
                        "Type": "RTID(modern_balloon@ZombieTypes)"
                    },
                    {
                        "Row": "5",
                        "Type": "RTID(disco_mech@ZombieTypes)"
                    }
                ]
            },
            "objclass": "SpawnZombiesJitteredWaveActionProps"
        },
        {
            "aliases": [
                "Wave16"
            ],
            "objdata": {
                "Zombies": [
                    {
                        "Row": "1",
                        "Type": "RTID(modern_balloon@ZombieTypes)"
                    },
                    {
                        "Row": "1",
                        "Type": "RTID(disco_mech@ZombieTypes)"
                    },
                    {
                        "Row": "1",
                        "Type": "RTID(ra@ZombieTypes)"
                    },
                    {
                        "Row": "1",
                        "Type": "RTID(modern_newspaper@ZombieTypes)"
                    },
                    {
                        "Row": "2",
                        "Type": "RTID(cowboy_gargantuar@ZombieTypes)"
                    },
                    {
                        "Row": "2",
                        "Type": "RTID(disco_mech@ZombieTypes)"
                    },
                    {
                        "Row": "2",
                        "Type": "RTID(modern_newspaper@ZombieTypes)"
                    },
                    {
                        "Row": "2",
                        "Type": "RTID(ra@ZombieTypes)"
                    },
                    {
                        "Row": "3",
                        "Type": "RTID(modern_balloon@ZombieTypes)"
                    },
                    {
                        "Row": "3",
                        "Type": "RTID(disco_mech@ZombieTypes)"
                    },
                    {
                        "Row": "3",
                        "Type": "RTID(ra@ZombieTypes)"
                    },
                    {
                        "Row": "3",
                        "Type": "RTID(modern_newspaper@ZombieTypes)"
                    },
                    {
                        "Row": "4",
                        "Type": "RTID(cowboy_gargantuar@ZombieTypes)"
                    },
                    {
                        "Row": "4",
                        "Type": "RTID(disco_mech@ZombieTypes)"
                    },
                    {
                        "Row": "4",
                        "Type": "RTID(modern_newspaper@ZombieTypes)"
                    },
                    {
                        "Row": "4",
                        "Type": "RTID(ra@ZombieTypes)"
                    },
                    {
                        "Row": "5",
                        "Type": "RTID(modern_balloon@ZombieTypes)"
                    },
                    {
                        "Row": "5",
                        "Type": "RTID(disco_mech@ZombieTypes)"
                    },
                    {
                        "Row": "5",
                        "Type": "RTID(ra@ZombieTypes)"
                    },
                    {
                        "Row": "5",
                        "Type": "RTID(modern_newspaper@ZombieTypes)"
                    }
                ]
            },
            "objclass": "SpawnZombiesJitteredWaveActionProps"
        },
        {
            "aliases": [
                "Wave17"
            ],
            "objdata": {
                "Zombies": [
                    {
                        "Row": "1",
                        "Type": "RTID(piano@ZombieTypes)"
                    },
                    {
                        "Row": "1",
                        "Type": "RTID(lostcity_impporter@ZombieTypes)"
                    },
                    {
                        "Row": "1",
                        "Type": "RTID(modern_newspaper@ZombieTypes)"
                    },
                    {
                        "Row": "2",
                        "Type": "RTID(modern_balloon@ZombieTypes)"
                    },
                    {
                        "Row": "2",
                        "Type": "RTID(disco_mech@ZombieTypes)"
                    },
                    {
                        "Row": "2",
                        "Type": "RTID(piano@ZombieTypes)"
                    },
                    {
                        "Row": "2",
                        "Type": "RTID(lostcity_impporter@ZombieTypes)"
                    },
                    {
                        "Row": "3",
                        "Type": "RTID(piano@ZombieTypes)"
                    },
                    {
                        "Row": "3",
                        "Type": "RTID(lostcity_impporter@ZombieTypes)"
                    },
                    {
                        "Row": "3",
                        "Type": "RTID(modern_newspaper@ZombieTypes)"
                    },
                    {
                        "Row": "4",
                        "Type": "RTID(modern_balloon@ZombieTypes)"
                    },
                    {
                        "Row": "4",
                        "Type": "RTID(disco_mech@ZombieTypes)"
                    },
                    {
                        "Row": "4",
                        "Type": "RTID(piano@ZombieTypes)"
                    },
                    {
                        "Row": "4",
                        "Type": "RTID(lostcity_impporter@ZombieTypes)"
                    },
                    {
                        "Row": "5",
                        "Type": "RTID(piano@ZombieTypes)"
                    },
                    {
                        "Row": "5",
                        "Type": "RTID(lostcity_impporter@ZombieTypes)"
                    },
                    {
                        "Row": "5",
                        "Type": "RTID(modern_newspaper@ZombieTypes)"
                    }
                ]
            },
            "objclass": "SpawnZombiesJitteredWaveActionProps"
        },
        {
            "aliases": [
                "Wave18"
            ],
            "objdata": {
                "Zombies": [
                    {
                        "Row": "1",
                        "Type": "RTID(cowboy_gargantuar@ZombieTypes)"
                    },
                    {
                        "Row": "1",
                        "Type": "RTID(modern_balloon@ZombieTypes)"
                    },
                    {
                        "Row": "1",
                        "Type": "RTID(disco_mech@ZombieTypes)"
                    },
                    {
                        "Row": "1",
                        "Type": "RTID(lostcity_impporter@ZombieTypes)"
                    },
                    {
                        "Row": "1",
                        "Type": "RTID(lostcity_impporter@ZombieTypes)"
                    },
                    {
                        "Row": "1",
                        "Type": "RTID(modern_newspaper@ZombieTypes)"
                    },
                    {
                        "Row": "1",
                        "Type": "RTID(modern_newspaper@ZombieTypes)"
                    },
                    {
                        "Row": "2",
                        "Type": "RTID(disco_mech@ZombieTypes)"
                    },
                    {
                        "Row": "2",
                        "Type": "RTID(lostcity_impporter@ZombieTypes)"
                    },
                    {
                        "Row": "2",
                        "Type": "RTID(lostcity_impporter@ZombieTypes)"
                    },
                    {
                        "Row": "2",
                        "Type": "RTID(ra@ZombieTypes)"
                    },
                    {
                        "Row": "2",
                        "Type": "RTID(modern_balloon@ZombieTypes)"
                    },
                    {
                        "Row": "2",
                        "Type": "RTID(modern_newspaper@ZombieTypes)"
                    },
                    {
                        "Row": "3",
                        "Type": "RTID(modern_balloon@ZombieTypes)"
                    },
                    {
                        "Row": "3",
                        "Type": "RTID(disco_mech@ZombieTypes)"
                    },
                    {
                        "Row": "3",
                        "Type": "RTID(cowboy_gargantuar@ZombieTypes)"
                    },
                    {
                        "Row": "3",
                        "Type": "RTID(lostcity_impporter@ZombieTypes)"
                    },
                    {
                        "Row": "3",
                        "Type": "RTID(ra@ZombieTypes)"
                    },
                    {
                        "Row": "3",
                        "Type": "RTID(modern_newspaper@ZombieTypes)"
                    },
                    {
                        "Row": "4",
                        "Type": "RTID(disco_mech@ZombieTypes)"
                    },
                    {
                        "Row": "4",
                        "Type": "RTID(lostcity_impporter@ZombieTypes)"
                    },
                    {
                        "Row": "4",
                        "Type": "RTID(lostcity_impporter@ZombieTypes)"
                    },
                    {
                        "Row": "4",
                        "Type": "RTID(modern_balloon@ZombieTypes)"
                    },
                    {
                        "Row": "4",
                        "Type": "RTID(modern_newspaper@ZombieTypes)"
                    },
                    {
                        "Row": "4",
                        "Type": "RTID(ra@ZombieTypes)"
                    },
                    {
                        "Row": "5",
                        "Type": "RTID(cowboy_gargantuar@ZombieTypes)"
                    },
                    {
                        "Row": "5",
                        "Type": "RTID(modern_balloon@ZombieTypes)"
                    },
                    {
                        "Row": "5",
                        "Type": "RTID(disco_mech@ZombieTypes)"
                    },
                    {
                        "Row": "5",
                        "Type": "RTID(lostcity_impporter@ZombieTypes)"
                    },
                    {
                        "Row": "5",
                        "Type": "RTID(lostcity_impporter@ZombieTypes)"
                    },
                    {
                        "Row": "5",
                        "Type": "RTID(modern_newspaper@ZombieTypes)"
                    },
                    {
                        "Row": "5",
                        "Type": "RTID(modern_newspaper@ZombieTypes)"
                    }
                ]
            },
            "objclass": "SpawnZombiesJitteredWaveActionProps"
        }
    ]
}