{
    "#comment": "Iceage 6",
    "objects": [
        {
            "objclass": "LevelDefinition",
            "objdata": {
                "Description": "[PLAYERS_EPIC_QUEST_ELECTRIC_CURRANT]",
                "FirstIntroNarrative": "EPIC_QUEST_ELECTRICCURRANT_2_INTRO",
                "LevelNumber": 2,
                "Loot": "RTID(DefaultLoot@LevelModules)",
                "Modules": [
                    "RTID(StandardIntro@LevelModules)",
                    "RTID(DefaultSunDropper@LevelModules)",
                    "RTID(ZombiesDeadWinCon@LevelModules)",
                    "RTID(IceageMowers@LevelModules)",
                    "RTID(SeedBank@CurrentLevel)",
                    "RTID(DefaultZombieWinCondition@LevelModules)",
                    "RTID(NewWaves@CurrentLevel)",
                    "RTID(SliderPlacement@CurrentLevel)",
                    "RTID(FrozenPlantPlacement@CurrentLevel)"
                ],
                "Name": "[EPIC_QUEST_ELECTRIC_CURRANT_LEVEL_NAME]",
                "NormalPresentTable": "egypt_normal_01",
                "ShinyPresentTable": "egypt_shiny_01",
                "StageModule": "RTID(IceageStage@LevelModules)"
            }
        },
        {
            "aliases": [
                "SliderPlacement"
            ],
            "objclass": "InitialGridItemProperties",
            "objdata": {
                "InitialGridItemPlacements": [
                    {
                        "GridX": 6,
                        "GridY": 0,
                        "TypeName": "slider_down"
                    },
                    {
                        "GridX": 6,
                        "GridY": 4,
                        "TypeName": "slider_up"
                    }
                ]
            }
        },
        {
            "aliases": [
                "FrozenPlantPlacement"
            ],
            "objclass": "InitialPlantProperties",
            "objdata": {
                "InitialPlantPlacements": [
                    {
                        "GridX": 5,
                        "GridY": 0,
                        "TypeName": "electriccurrant"
                    },
                    {
                        "GridX": 5,
                        "GridY": 4,
                        "TypeName": "electriccurrant"
                    }
                ]
            }
        },
        {
            "aliases": [
                "SeedBank"
            ],
            "objclass": "SeedBankProperties",
            "objdata": {
                "PresetPlantList": [
                    {
                        "PlantType": "electriccurrant",
                        "Level": -1
                    },
                    {
                        "PlantType": "sunflower",
                        "Level": -1
                    },
                    {
                        "PlantType": "spikeweed",
                        "Level": -1
                    },
                    {
                        "PlantType": "wallnut",
                        "Level": -1
                    }
                ],
                "SelectionMethod": "chooser"
            }
        },
        {
            "aliases": [
                "NewWaves"
            ],
            "objclass": "WaveManagerModuleProperties",
            "objdata": {
                "DynamicZombies": [
                    {
                        "PointIncrementPerWave": -40,
                        "StartingPoints": -100,
                        "StartingWave": 3,
                        "ZombiePool": [
                            "RTID(future@ZombieTypes)",
                            "RTID(future_armor1@ZombieTypes)",
                            "RTID(future_jetpack@ZombieTypes)",
                            "RTID(lostcity_relichunter@ZombieTypes)"
                        ]
                    },
                    {
                        "PointIncrementPerWave": -25,
                        "StartingPoints": -100,
                        "StartingWave": 4,
                        "ZombiePool": [
                            "RTID(future@ZombieTypes)",
                            "RTID(future_armor1@ZombieTypes)",
                            "RTID(future_jetpack@ZombieTypes)",
                            "RTID(lostcity_relichunter@ZombieTypes)"
                        ]
                    },
                    {
                        "PointIncrementPerWave": -10,
                        "StartingPoints": -100,
                        "StartingWave": 5,
                        "ZombiePool": [
                            "RTID(future@ZombieTypes)",
                            "RTID(future_armor1@ZombieTypes)",
                            "RTID(future_jetpack@ZombieTypes)",
                            "RTID(lostcity_relichunter@ZombieTypes)"
                        ]
                    },
                    {},
                    {
                        "PointIncrementPerWave": 20,
                        "StartingPoints": 100,
                        "StartingWave": 5,
                        "ZombiePool": [
                            "RTID(future@ZombieTypes)",
                            "RTID(future_armor1@ZombieTypes)",
                            "RTID(future_jetpack@ZombieTypes)",
                            "RTID(lostcity_relichunter@ZombieTypes)"
                        ]
                    },
                    {
                        "PointIncrementPerWave": 40,
                        "StartingPoints": 200,
                        "StartingWave": 4,
                        "ZombiePool": [
                            "RTID(future_armor1@ZombieTypes)",
                            "RTID(future_jetpack@ZombieTypes)",
                            "RTID(lostcity_relichunter@ZombieTypes)"
                        ]
                    },
                    {
                        "PointIncrementPerWave": 60,
                        "StartingPoints": 400,
                        "StartingWave": 3,
                        "ZombiePool": [
                            "RTID(future_jetpack@ZombieTypes)",
                            "RTID(lostcity_relichunter@ZombieTypes)"
                        ]
                    }
                ],
                "WaveManagerProps": "RTID(WaveManagerProps@CurrentLevel)"
            }
        },
        {
            "aliases": [
                "WaveManagerProps"
            ],
            "objclass": "WaveManagerProperties",
            "objdata": {
                "FlagWaveInterval": 5,
                "WaveCount": 10,
                "WaveSpendingPointIncrement": 100,
                "WaveSpendingPoints": 100,
                "Waves": [
                    [
                        "RTID(Wave1@CurrentLevel)"
                    ],
                    [
                        "RTID(Wave2@CurrentLevel)"
                    ],
                    [
                        "RTID(Wave3@CurrentLevel)"
                    ],
                    [
                        "RTID(Wave4@CurrentLevel)"
                    ],
                    [
                        "RTID(Wave5@CurrentLevel)"
                    ],
                    [
                        "RTID(Wave6@CurrentLevel)"
                    ],
                    [
                        "RTID(Wave7@CurrentLevel)"
                    ],
                    [
                        "RTID(Wave8@CurrentLevel)"
                    ],
                    [
                        "RTID(Wave9@CurrentLevel)"
                    ],
                    [
                        "RTID(Wave10@CurrentLevel)"
                    ]
                ]
            }
        },
        {
            "aliases": [
                "Wave1"
            ],
            "objclass": "SpawnZombiesJitteredWaveActionProps",
            "objdata": {
                "AdditionalPlantfood": 0,
                "Zombies": [
                    {
                        "Row": "5",
                        "Type": "RTID(future@ZombieTypes)"
                    },
                    {
                        "Row": "1",
                        "Type": "RTID(future@ZombieTypes)"
                    },
                    {
                        "Row": "3",
                        "Type": "RTID(future@ZombieTypes)"
                    }
                ]
            }
        },
        {
            "aliases": [
                "Wave2"
            ],
            "objclass": "SpawnZombiesJitteredWaveActionProps",
            "objdata": {
                "AdditionalPlantfood": 0,
                "Zombies": [
                    {
                        "Row": "4",
                        "Type": "RTID(future@ZombieTypes)"
                    },
                    {
                        "Row": "3",
                        "Type": "RTID(future_armor1@ZombieTypes)"
                    },
                    {
                        "Row": "3",
                        "Type": "RTID(future_armor1@ZombieTypes)"
                    },
                    {
                        "Row": "2",
                        "Type": "RTID(future@ZombieTypes)"
                    }
                ]
            }
        },
        {
            "aliases": [
                "Wave3"
            ],
            "objclass": "SpawnZombiesJitteredWaveActionProps",
            "objdata": {
                "AdditionalPlantfood": 1,
                "DynamicPlantfood": [
                    1,
                    1,
                    1,
                    1,
                    0,
                    0,
                    0
                ],
                "Zombies": [
                    {
                        "Row": "4",
                        "Type": "RTID(future@ZombieTypes)"
                    },
                    {
                        "Row": "3",
                        "Type": "RTID(future_armor2@ZombieTypes)"
                    },
                    {
                        "Row": "3",
                        "Type": "RTID(future_protector@ZombieTypes)"
                    },
                    {
                        "Row": "2",
                        "Type": "RTID(future@ZombieTypes)"
                    }
                ]
            }
        },
        {
            "aliases": [
                "Wave4"
            ],
            "objclass": "SpawnZombiesJitteredWaveActionProps",
            "objdata": {
                "AdditionalPlantfood": 0,
                "Zombies": [
                    {
                        "Row": "5",
                        "Type": "RTID(future@ZombieTypes)"
                    },
                    {
                        "Row": "4",
                        "Type": "RTID(swashbuckler@ZombieTypes)"
                    },
                    {
                        "Row": "4",
                        "Type": "RTID(iceage_weaselhoarder@ZombieTypes)"
                    },
                    {
                        "Row": "2",
                        "Type": "RTID(iceage_weaselhoarder@ZombieTypes)"
                    },
                    {
                        "Row": "1",
                        "Type": "RTID(future@ZombieTypes)"
                    }
                ]
            }
        },
        {
            "aliases": [
                "Wave5"
            ],
            "objclass": "SpawnZombiesJitteredWaveActionProps",
            "objdata": {
                "AdditionalPlantfood": 1,
                "DynamicPlantfood": [
                    1,
                    1,
                    1,
                    1,
                    1,
                    1,
                    1
                ],
                "Zombies": [
                    {
                        "Row": "5",
                        "Type": "RTID(future_protector@ZombieTypes)"
                    },
                    {
                        "Row": "5",
                        "Type": "RTID(future@ZombieTypes)"
                    },
                    {
                        "Row": "5",
                        "Type": "RTID(swashbuckler@ZombieTypes)"
                    },
                    {
                        "Row": "4",
                        "Type": "RTID(future_jetpack@ZombieTypes)"
                    },
                    {
                        "Row": "4",
                        "Type": "RTID(future@ZombieTypes)"
                    },
                    {
                        "Row": "3",
                        "Type": "RTID(future_jetpack@ZombieTypes)"
                    },
                    {
                        "Row": "3",
                        "Type": "RTID(swashbuckler@ZombieTypes)"
                    },
                    {
                        "Row": "2",
                        "Type": "RTID(future_jetpack@ZombieTypes)"
                    },
                    {
                        "Row": "2",
                        "Type": "RTID(future@ZombieTypes)"
                    },
                    {
                        "Row": "1",
                        "Type": "RTID(future_protector@ZombieTypes)"
                    },
                    {
                        "Row": "1",
                        "Type": "RTID(future@ZombieTypes)"
                    },
                    {
                        "Row": "1",
                        "Type": "RTID(swashbuckler@ZombieTypes)"
                    }
                ]
            }
        },
        {
            "aliases": [
                "Wave6"
            ],
            "objclass": "SpawnZombiesJitteredWaveActionProps",
            "objdata": {
                "Zombies": [
                    {
                        "Row": "5",
                        "Type": "RTID(future_jetpack@ZombieTypes)"
                    },
                    {
                        "Row": "4",
                        "Type": "RTID(swashbuckler@ZombieTypes)"
                    },
                    {
                        "Row": "4",
                        "Type": "RTID(lostcity_relichunter@ZombieTypes)"
                    },
                    {
                        "Row": "3",
                        "Type": "RTID(swashbuckler@ZombieTypes)"
                    },
                    {
                        "Row": "3",
                        "Type": "RTID(lostcity_relichunter@ZombieTypes)"
                    },
                    {
                        "Row": "2",
                        "Type": "RTID(swashbuckler@ZombieTypes)"
                    },
                    {
                        "Row": "2",
                        "Type": "RTID(lostcity_relichunter@ZombieTypes)"
                    },
                    {
                        "Row": "1",
                        "Type": "RTID(future_jetpack@ZombieTypes)"
                    }
                ]
            }
        },
        {
            "aliases": [
                "Wave7"
            ],
            "objclass": "SpawnZombiesJitteredWaveActionProps",
            "objdata": {
                "AdditionalPlantfood": 0,
                "Zombies": [
                    {
                        "Row": "5",
                        "Type": "RTID(lostcity_relichunter@ZombieTypes)"
                    },
                    {
                        "Row": "4",
                        "Type": "RTID(future_jetpack@ZombieTypes)"
                    },
                    {
                        "Row": "4",
                        "Type": "RTID(future_armor1@ZombieTypes)"
                    },
                    {
                        "Row": "3",
                        "Type": "RTID(future_jetpack@ZombieTypes)"
                    },
                    {
                        "Row": "3",
                        "Type": "RTID(future_jetpack@ZombieTypes)"
                    },
                    {
                        "Row": "2",
                        "Type": "RTID(future_jetpack@ZombieTypes)"
                    },
                    {
                        "Row": "2",
                        "Type": "RTID(future_armor1@ZombieTypes)"
                    },
                    {
                        "Row": "1",
                        "Type": "RTID(lostcity_relichunter@ZombieTypes)"
                    }
                ]
            }
        },
        {
            "aliases": [
                "Wave8"
            ],
            "objclass": "SpawnZombiesJitteredWaveActionProps",
            "objdata": {
                "AdditionalPlantfood": 1,
                "DynamicPlantfood": [
                    1,
                    1,
                    1,
                    1,
                    1,
                    0,
                    0
                ],
                "Zombies": [
                    {
                        "Row": "5",
                        "Type": "RTID(iceage_weaselhoarder@ZombieTypes)"
                    },
                    {
                        "Row": "4",
                        "Type": "RTID(iceage_weaselhoarder@ZombieTypes)"
                    },
                    {
                        "Row": "3",
                        "Type": "RTID(iceage_weaselhoarder@ZombieTypes)"
                    },
                    {
                        "Row": "2",
                        "Type": "RTID(iceage_weaselhoarder@ZombieTypes)"
                    },
                    {
                        "Row": "1",
                        "Type": "RTID(iceage_weaselhoarder@ZombieTypes)"
                    }
                ]
            }
        },
        {
            "aliases": [
                "Wave9"
            ],
            "objclass": "SpawnZombiesJitteredWaveActionProps",
            "objdata": {
                "AdditionalPlantfood": 0,
                "Zombies": [
                    {
                        "Row": "4",
                        "Type": "RTID(lostcity_relichunter@ZombieTypes)"
                    },
                    {
                        "Row": "4",
                        "Type": "RTID(lostcity_relichunter@ZombieTypes)"
                    },
                    {
                        "Row": "3",
                        "Type": "RTID(lostcity_relichunter@ZombieTypes)"
                    },
                    {
                        "Row": "3",
                        "Type": "RTID(lostcity_relichunter@ZombieTypes)"
                    },
                    {
                        "Row": "2",
                        "Type": "RTID(lostcity_relichunter@ZombieTypes)"
                    },
                    {
                        "Row": "2",
                        "Type": "RTID(lostcity_relichunter@ZombieTypes)"
                    },
                    {
                        "Row": "5",
                        "Type": "RTID(future_armor2@ZombieTypes)"
                    },
                    {
                        "Row": "4",
                        "Type": "RTID(future_protector@ZombieTypes)"
                    },
                    {
                        "Row": "3",
                        "Type": "RTID(future_armor2@ZombieTypes)"
                    },
                    {
                        "Row": "2",
                        "Type": "RTID(future_protector@ZombieTypes)"
                    },
                    {
                        "Row": "1",
                        "Type": "RTID(future_armor2@ZombieTypes)"
                    }
                ]
            }
        },
        {
            "aliases": [
                "Wave10"
            ],
            "objclass": "SpawnZombiesJitteredWaveActionProps",
            "objdata": {
                "AdditionalPlantfood": 0,
                "Zombies": [
                    {
                        "Row": "5",
                        "Type": "RTID(future_jetpack@ZombieTypes)"
                    },
                    {
                        "Row": "5",
                        "Type": "RTID(iceage_weaselhoarder@ZombieTypes)"
                    },
                    {
                        "Row": "4",
                        "Type": "RTID(future_jetpack@ZombieTypes)"
                    },
                    {
                        "Row": "4",
                        "Type": "RTID(future_armor2@ZombieTypes)"
                    },
                    {
                        "Row": "4",
                        "Type": "RTID(football_mech@ZombieTypes)"
                    },
                    {
                        "Row": "3",
                        "Type": "RTID(future_jetpack@ZombieTypes)"
                    },
                    {
                        "Row": "3",
                        "Type": "RTID(future_armor2@ZombieTypes)"
                    },
                    {
                        "Row": "3",
                        "Type": "RTID(future_armor2@ZombieTypes)"
                    },
                    {
                        "Row": "3",
                        "Type": "RTID(iceage_weaselhoarder@ZombieTypes)"
                    },
                    {
                        "Row": "2",
                        "Type": "RTID(future_jetpack@ZombieTypes)"
                    },
                    {
                        "Row": "2",
                        "Type": "RTID(future_armor2@ZombieTypes)"
                    },
                    {
                        "Row": "2",
                        "Type": "RTID(football_mech@ZombieTypes)"
                    },
                    {
                        "Row": "1",
                        "Type": "RTID(future_jetpack@ZombieTypes)"
                    },
                    {
                        "Row": "1",
                        "Type": "RTID(iceage_weaselhoarder@ZombieTypes)"
                    }
                ]
            }
        }
    ],
    "version": 1
}